BeginnersbookCJiaochengChuyiFix1/README.md
BeginnersbookCJiaochengChuyiFix1/__init__.py
BeginnersbookCJiaochengChuyiFix1/__main__.py
BeginnersbookCJiaochengChuyiFix1/file.epub
BeginnersbookCJiaochengChuyiFix1/index.html
BeginnersbookCJiaochengChuyiFix1/css/__init__.py
BeginnersbookCJiaochengChuyiFix1/css/annotations.css
BeginnersbookCJiaochengChuyiFix1/css/main.css
BeginnersbookCJiaochengChuyiFix1/css/normalize.css
BeginnersbookCJiaochengChuyiFix1/css/popup.css
BeginnersbookCJiaochengChuyiFix1/font/__init__.py
BeginnersbookCJiaochengChuyiFix1/font/fontello.eot
BeginnersbookCJiaochengChuyiFix1/font/fontello.svg
BeginnersbookCJiaochengChuyiFix1/font/fontello.ttf
BeginnersbookCJiaochengChuyiFix1/font/fontello.woff
BeginnersbookCJiaochengChuyiFix1/img/__init__.py
BeginnersbookCJiaochengChuyiFix1/img/annotator-glyph-sprite.png
BeginnersbookCJiaochengChuyiFix1/img/annotator-icon-sprite.png
BeginnersbookCJiaochengChuyiFix1/img/apple-touch-icon.png
BeginnersbookCJiaochengChuyiFix1/img/cancelfullscreen.png
BeginnersbookCJiaochengChuyiFix1/img/close.png
BeginnersbookCJiaochengChuyiFix1/img/fullscreen.png
BeginnersbookCJiaochengChuyiFix1/img/loader.gif
BeginnersbookCJiaochengChuyiFix1/img/menu-icon.png
BeginnersbookCJiaochengChuyiFix1/img/save.png
BeginnersbookCJiaochengChuyiFix1/img/saved.png
BeginnersbookCJiaochengChuyiFix1/img/settings-s.png
BeginnersbookCJiaochengChuyiFix1/img/settings.png
BeginnersbookCJiaochengChuyiFix1/img/star.png
BeginnersbookCJiaochengChuyiFix1/js/__init__.py
BeginnersbookCJiaochengChuyiFix1/js/epub.js
BeginnersbookCJiaochengChuyiFix1/js/epub.min.js
BeginnersbookCJiaochengChuyiFix1/js/epub.min.map
BeginnersbookCJiaochengChuyiFix1/js/hooks.min.js
BeginnersbookCJiaochengChuyiFix1/js/hooks.min.map
BeginnersbookCJiaochengChuyiFix1/js/reader.js
BeginnersbookCJiaochengChuyiFix1/js/reader.js.map
BeginnersbookCJiaochengChuyiFix1/js/reader.min.js
BeginnersbookCJiaochengChuyiFix1/js/reader.min.map
BeginnersbookCJiaochengChuyiFix1/js/hooks/__init__.py
beginnersbook_c_jiaocheng_chuyi_fix1-2025.3.23.0.dist-info/METADATA
beginnersbook_c_jiaocheng_chuyi_fix1-2025.3.23.0.dist-info/WHEEL
beginnersbook_c_jiaocheng_chuyi_fix1-2025.3.23.0.dist-info/entry_points.txt
beginnersbook_c_jiaocheng_chuyi_fix1-2025.3.23.0.dist-info/top_level.txt
beginnersbook_c_jiaocheng_chuyi_fix1-2025.3.23.0.dist-info/RECORD
